herming
