Metadata-Version: 1.0
Name: herming
Version: 1.2
Summary: for you
Home-page: http://github.com/tongling/ab_resbase
Author: herming
Author-email: an520999@gmail.com
License: JUST
Platform: UNKNOWN
